hyponic/__init__.py
hyponic/hyponic.py
hyponic/space.py
hyponic/metrics/__init__.py
hyponic/metrics/classification.py
hyponic/metrics/decorators.py
hyponic/metrics/regression.py
hyponic/optimizers/__init__.py
hyponic/optimizers/base_optimizer.py
hyponic/optimizers/genetic_based/GA.py
hyponic/optimizers/genetic_based/__init__.py
hyponic/optimizers/physics_based/SA.py
hyponic/optimizers/physics_based/__init__.py
hyponic/optimizers/swarm_based/ABC.py
hyponic/optimizers/swarm_based/ACO.py
hyponic/optimizers/swarm_based/CS.py
hyponic/optimizers/swarm_based/GWO.py
hyponic/optimizers/swarm_based/PSO.py
hyponic/optimizers/swarm_based/__init__.py
hyponic/utils/__init__.py
hyponic/utils/history.py
hyponic/utils/problem_identifier.py
hyponic/utils/symtable.py
hyponic-0.1.1.dist-info/LICENSE
hyponic-0.1.1.dist-info/METADATA
hyponic-0.1.1.dist-info/WHEEL
hyponic-0.1.1.dist-info/top_level.txt
hyponic-0.1.1.dist-info/RECORD
