Metadata-Version: 2.1
Name: hyponic
Version: 0.1.1
Summary: Hyperparameter Optimization with Nature-Inspired Computing
Home-page: https://github.com/slewie/HypONIC
Author: Vladislav Kulikov, Daniel Satarov, Ivan Chernakov
Author-email: v.kulikov@innopolis.university, d.satarov@innopolis.university, i.chernakov@innopolis.university
Classifier: Programming Language :: Python :: 3.11
Classifier: License :: OSI Approved :: MIT License
Classifier: Operating System :: OS Independent
Requires-Python: >=3.10
License-File: LICENSE
Requires-Dist: numpy (>=1.23.5)
Requires-Dist: numexpr (>=2.8.4)
Requires-Dist: numba (>=0.57.0)
Requires-Dist: matplotlib (>=3.6.3)
